kubetest/__init__.py
kubetest/client.py
kubetest/condition.py
kubetest/errors.py
kubetest/manager.py
kubetest/manifest.py
kubetest/markers.py
kubetest/plugin.py
kubetest/response.py
kubetest/utils.py
kubetest/objects/__init__.py
kubetest/objects/api_object.py
kubetest/objects/clusterrolebinding.py
kubetest/objects/configmap.py
kubetest/objects/container.py
kubetest/objects/daemonset.py
kubetest/objects/deployment.py
kubetest/objects/endpoints.py
kubetest/objects/event.py
kubetest/objects/ingress.py
kubetest/objects/namespace.py
kubetest/objects/networkpolicy.py
kubetest/objects/node.py
kubetest/objects/persistentvolumeclaim.py
kubetest/objects/pod.py
kubetest/objects/replicaset.py
kubetest/objects/rolebinding.py
kubetest/objects/secret.py
kubetest/objects/service.py
kubetest/objects/serviceaccount.py
kubetest/objects/statefulset.py
kubetest-0.9.5.dist-info/LICENSE
kubetest-0.9.5.dist-info/METADATA
kubetest-0.9.5.dist-info/WHEEL
kubetest-0.9.5.dist-info/entry_points.txt
kubetest-0.9.5.dist-info/top_level.txt
kubetest-0.9.5.dist-info/RECORD
