Metadata-Version: 2.1
Name: kubetest
Version: 0.9.5
Summary: A Kubernetes integration test framework in Python.
Home-page: https://github.com/vapor-ware/kubetest
Author: Vapor IO
Author-email: vapor@vapor.io
License: GNU General Public License v3.0
Platform: UNKNOWN
Classifier: Environment :: Plugins
Classifier: Framework :: Pytest
Classifier: Intended Audience :: Developers
Classifier: Natural Language :: English
Classifier: Programming Language :: Python
Classifier: Programming Language :: Python :: 3
Classifier: Programming Language :: Python :: 3.6
Requires-Python: >=3.6
Requires-Dist: kubernetes (>=12.0.0)
Requires-Dist: pyyaml (>=4.2b1)
Requires-Dist: pytest
